fastapi_auth_middleware/__init__.py
fastapi_auth_middleware/exceptions.py
fastapi_auth_middleware/middleware.py
fastapi_auth_middleware/oauth2_middleware.py
fastapi_auth_middleware-1.0.2.dist-info/LICENSE
fastapi_auth_middleware-1.0.2.dist-info/WHEEL
fastapi_auth_middleware-1.0.2.dist-info/METADATA
fastapi_auth_middleware-1.0.2.dist-info/RECORD
