Metadata-Version: 2.1
Name: fastapi_auth_middleware
Version: 1.0.2
Summary: Lightweight auth middleware for FastAPI that just works. Fits most auth workflows with only a few lines of code. 
Keywords: FastAPI,Auth,Middleware,Authentication,Authorization
Author-email: Jonas Scholl <jonas@code-specialist.com>, Yannic Schröer <yannic@code-specialist.com>
Maintainer-email: Jonas Scholl <jonas@code-specialist.com>, Yannic Schröer <yannic@code-specialist.com>
Requires-Python: >=3.8
Classifier: Development Status :: 3 - Alpha
Classifier: Intended Audience :: Developers
Classifier: Topic :: Internet :: WWW/HTTP :: Session
Classifier: Topic :: Internet :: WWW/HTTP :: WSGI
Classifier: Topic :: Software Development :: Libraries :: Application Frameworks
Classifier: Topic :: Software Development :: Libraries :: Python Modules
Classifier: Framework :: FastAPI
Classifier: License :: OSI Approved :: Apache Software License
Classifier: Programming Language :: Python :: 3.8
Requires-Dist: anyio>=3.5.0
Requires-Dist: fastapi>=0.73.0
Requires-Dist: idna>=3.3
Requires-Dist: pydantic>=1.9.0
Requires-Dist: sniffio>=1.2.0
Requires-Dist: starlette>=0.17.1
Requires-Dist: typing_extensions>=4.0.1
Requires-Dist: python-jose>=3.3.0
Project-URL: Documentation, https://github.com/code-specialist/fastapi-auth-middleware
Project-URL: Source, https://github.com/code-specialist/fastapi-auth-middleware
